Metadata-Version: 2.1
Name: rvr
Version: 0.0.2
Summary: A wrapper for RVR.
Home-page: https://github.com/Aermoss/PyRVR
Author: Yusuf Rençber
Author-email: aermoss.0@gmail.com
License: MIT
License-File: LICENSE
